pynlpclassifier/__init__.py
pynlpclassifier/main.py
pynlpclassifier/utils.py
pynlpclassifier-0.1.12.dist-info/METADATA
pynlpclassifier-0.1.12.dist-info/WHEEL
pynlpclassifier-0.1.12.dist-info/top_level.txt
pynlpclassifier-0.1.12.dist-info/RECORD
